{
  "id": 617,
  "title": null,
  "slug": "160527-",
  "body": "<div style=\"padding: 100% 0 0 0; position: relative;\"><iframe style=\"position: absolute; top: 0; left: 0; width: 100%; height: 100%;\" src=\"https://player.vimeo.com/video/321202244?badge=0&amp;autopause=0&amp;player_id=0&amp;app_id=58479\" frameborder=\"0\" allow=\"autoplay; fullscreen; picture-in-picture; clipboard-write; encrypted-media; web-share\" referrerpolicy=\"strict-origin-when-cross-origin\"></iframe></div>\n<p>The next offering in our series of Friday vignettes comes courtesy of <a href=\"http://adam-buxton.co.uk/ad/\">Adam Buxton</a>.</p>",
  "signature": null,
  "images": [],
  "date": "Fri, 27th May 2016"
}