{
  "id": 378,
  "title": "Hey what are you doing tomorrow night?",
  "slug": "091002-hey-what-are-you-doing-tomorrow-night",
  "body": "ok now with a link that works hopefully<br><br>so yes that band thats doesnt really have a name that im working with at the moment??????<br>have decided to do a  warm-up show on Friday Oct 2nd around 9pm at the Echoplex in Los Angeles<br>Its not that big, it'll be total chaos and its kind of a rehearsal but .. if you are near by..<br>below is a link to get tickets. <br>hope you get lucky with it.<br><br>so ain't no point hanging around if u dont im afraid<br><br><br>all the best<br><br><a class='bol' target='_blank' href=\"http://www.ticketweb.com/t3/sale/SaleEventDetail?dispatch=loadSelectionData&eventId=2848604\">HERE go on work this time!</a>",
  "signature": "Thom",
  "images": [],
  "date": "Fri, 2nd October 2009"
}