{
  "id": 418,
  "title": "if you want it",
  "slug": "100510-if-you-want-it",
  "body": "<a class='bol' target='_blank' href=\"http://www.350.org/\"><font style=\"font-size: 15px;\">350.org</font></a><br><br>2010 is the year that America and the World decides our destiny is not tied to the suicide mission of the oil companies and the notion of limitless growth. it's over. happy christmas war is over. if you want it.<br>this website is organised by Bill McKibben. the perfect person for the job.<br>",
  "signature": "Thom",
  "images": [],
  "date": "Mon, 10th May 2010"
}